zfx/__init__.py
zfx/g2g_csgo_account_list.py
zfx/g2g_csgo_account_list_s.py
zfx/zmodule_240414A.py
zfx/zprint.py
zfx/系统任务计划_创建.py
zfx/系统任务计划_删除.py
zfx/系统任务计划_遍历名称.py
zfx-240425.1.dist-info/METADATA
zfx-240425.1.dist-info/WHEEL
zfx-240425.1.dist-info/top_level.txt
zfx-240425.1.dist-info/RECORD
