Metadata-Version: 2.1
Name: zfx
Version: 240425.1
Summary: 自用
Home-page: 
Author: zengfengxiang
Author-email: 424491679@qq.com
Requires-Dist: requests
